alu/full_adder.v
module full_adder(S, Cout, A, B, Cin);
    input A, B, Cin;
    output S, Cout; 
    wire w1, w2, w3;
    xor SUMS(S, A, B, Cin);
    and AND1(w1, A, B);
    and AND2(w2, A, Cin);
    and AND3(w3, B, Cin);
    or(Cout, w1, w2, w3);
endmodule

full_adder_tb.v
`timescale 1ns/100ps

module full_adder_tb;
    reg A, B, Cin; 
    wire S, Cout; 

    full_adder adder(.A(A), .B(B), .Cin(Cin), .S(S), .Cout(Cout));

    initial begin 
        A =0;
        B =0;
    Cin =0; 
    #80 
    $finish;
    end

    always 
        #10 A = ~A;
    always
        #20 B = ~B;
    always
        #40 Cin = ~Cin;

    always @(A, B, Cin) begin 
        #1 
        $display("A:%b, B:%b, Cin:%b => S:%b, Cout:%b", A, B, Cin, S, Cout);
    end 

    initial begin 
        $dumpfile("full_adder.vcd");
        $dumpvars(0, full_adder_tb);
    end 
endmodule

full_adder.vcd
$date
	Tue Aug 30 19:36:14 2022
$end
$version
	Icarus Verilog
$end
$timescale
	100ps
$end
$scope module full_adder_tb $end
$var wire 1 ! S $end
$var wire 1 " Cout $end
$var reg 1 # A $end
$var reg 1 $ B $end
$var reg 1 % Cin $end
$scope module adder $end
$var wire 1 # A $end
$var wire 1 $ B $end
$var wire 1 % Cin $end
$var wire 1 " Cout $end
$var wire 1 ! S $end
$var wire 1 & w1 $end
$var wire 1 ' w2 $end
$var wire 1 ( w3 $end
$upscope $end
$upscope $end
$enddefinitions $end
#0
$dumpvars
0(
0'
0&
0%
0$
0#
0"
0!
$end
#100
1!
1#
#200
0#
1$
#300
1"
0!
1&
1#
#400
0"
0&
1!
0#
0$
1%
#500
1"
0!
1'
1#
#600
0'
1(
0#
1$
#700
1!
1&
1'
1#
#800
0"
0&
0!
0'
0(
0#
0$
0%
